<annotation>
	<folder>test</folder>
	<filename>g84.jpg</filename>
	<path>D:\computervision\teamproject3\image\test\g84.jpg</path>
	<source>
		<database>Unknown</database>
	</source>
	<size>
		<width>3024</width>
		<height>3024</height>
		<depth>3</depth>
	</size>
	<segmented>0</segmented>
	<object>
		<name>oreo</name>
		<pose>Unspecified</pose>
		<truncated>1</truncated>
		<difficult>0</difficult>
		<bndbox>
			<xmin>559</xmin>
			<ymin>2030</ymin>
			<xmax>2747</xmax>
			<ymax>3024</ymax>
		</bndbox>
	</object>
	<object>
		<name>ggoggalcon</name>
		<pose>Unspecified</pose>
		<truncated>1</truncated>
		<difficult>0</difficult>
		<bndbox>
			<xmin>103</xmin>
			<ymin>1</ymin>
			<xmax>2800</xmax>
			<ymax>2326</ymax>
		</bndbox>
	</object>
</annotation>
